setup.py
represent_representatives.egg-info/PKG-INFO
represent_representatives.egg-info/SOURCES.txt
represent_representatives.egg-info/dependency_links.txt
represent_representatives.egg-info/requires.txt
represent_representatives.egg-info/top_level.txt
representatives/__init__.py
representatives/admin.py
representatives/models.py
representatives/urls.py
representatives/utils.py
representatives/views.py
representatives/management/__init__.py
representatives/management/commands/__init__.py
representatives/management/commands/updaterepresentatives.py