Metadata-Version: 1.1
Name: represent-representatives
Version: 0.1
Summary: A Web API for political representatives tied to geographical districts. Packaged as a Django app.
Home-page: https://github.com/rhymeswithcycle/represent-reps
Author: UNKNOWN
Author-email: UNKNOWN
License: UNKNOWN
Platform: UNKNOWN
Classifier: Programming Language :: Python :: 2.7
Classifier: License :: OSI Approved :: MIT License
Classifier: Framework :: Django
